ubud/__init__.py
ubud/const.py
ubud/scripts.py
ubud/api/__init__.py
ubud/api/base.py
ubud/api/bithumb.py
ubud/api/bithumb_api.py
ubud/api/forex.py
ubud/api/ftx.py
ubud/api/ftx_api.py
ubud/api/unified.py
ubud/api/upbit.py
ubud/api/upbit_api.py
ubud/connector/__init__.py
ubud/connector/console_log.py
ubud/connector/influxdb_sink.py
ubud/logging/__init__.py
ubud/logging/handlers.py
ubud/logging/listener.py
ubud/redis/__init__.py
ubud/redis/collector.py
ubud/redis/db.py
ubud/redis/streamer.py
ubud/utils/__init__.py
ubud/utils/utils.py
ubud/websocket/__init__.py
ubud/websocket/base.py
ubud/websocket/bithumb.py
ubud/websocket/ftx.py
ubud/websocket/upbit.py
ubud-2022.7.3.dist-info/METADATA
ubud-2022.7.3.dist-info/WHEEL
ubud-2022.7.3.dist-info/dependency_links.txt
ubud-2022.7.3.dist-info/entry_points.txt
ubud-2022.7.3.dist-info/top_level.txt
ubud-2022.7.3.dist-info/RECORD
