Metadata-Version: 2.1
Name: ubud
Version: 2022.7.3
Author: Woojin Cho
Author-email: woojin.cho@gmail.com
License: MIT License
Requires-Python: >=3.8
Requires-Dist: aiohttp
Requires-Dist: apscheduler
Requires-Dist: click
Requires-Dist: click-loglevel
Requires-Dist: clutter
Requires-Dist: python-dotenv
Requires-Dist: parse
Requires-Dist: pyjwt
Requires-Dist: pyyaml
Requires-Dist: pyzmq
Requires-Dist: flatdict
Requires-Dist: pendulum
Requires-Dist: pydantic
Requires-Dist: requests
Requires-Dist: influxdb-client
Requires-Dist: paho-mqtt
Requires-Dist: websockets
Requires-Dist: redis
Requires-Dist: rel
